LICENSE.txt
MANIFEST.in
README.rst
ecys.py
setup.py
ecys.egg-info/PKG-INFO
ecys.egg-info/SOURCES.txt
ecys.egg-info/dependency_links.txt
ecys.egg-info/top_level.txt