Metadata-Version: 1.0
Name: ecys
Version: 1.2.0
Summary: A simple realization of Entity Component System
Home-page: https://github.com/Djerys/ecys
Author: Dmitry Kotukhov
Author-email: djerys@ya.ru
License: MIT
Platform: UNKNOWN
